allnc/__init__.py
allnc/app.py
allnc/middleware.py
allnc/response.py
allnc-0.1.2.dist-info/METADATA
allnc-0.1.2.dist-info/WHEEL
allnc-0.1.2.dist-info/top_level.txt
allnc-0.1.2.dist-info/RECORD
